{
    "Icon":"icon.png",
    "Head":{
        "ModelName":"name.obj",
        "TextureName":"texture.png",
        "Width":2.0,
        "Height":2.0,
        "Weight":1000,
        "ConnectDistance":1.5,
        "Seats":[
            {"SeatSize":0.9, "LocalPosition":{"x":0, "y":0.4, "z":0}, "LocalRotationDegree":{"x":0, "y":0.4, "z":0}},
            {"SeatSize":0.9, "LocalPosition":{"x":0, "y":0.4, "z":0}, "LocalRotationDegree":{"x":0, "y":0.4, "z":1.0}}
        ]
    },
    "Connect":{
        "ModelName":"name.obj",
        "TextureName":"texture.png",
        "Width":2.0,
        "Height":2.0,
        "Weight":1000,
        "ConnectDistance":1.5,
        "Seats":[
            {"SeatSize":0.9, "LocalPosition":{"x":0, "y":0.4, "z":0}, "LocalRotationDegree":{"x":0, "y":0.4, "z":0}},
            {"SeatSize":0.9, "LocalPosition":{"x":0, "y":0.4, "z":0}, "LocalRotationDegree":{"x":0, "y":0.4, "z":1.0}}
        ]
    }
}